bernn/__init__.py
bernn/_version.py
bernn/config/__init__.py
bernn/config/training_config.py
bernn/dl/__init__.py
bernn/dl/models/__init__.py
bernn/dl/models/pytorch/__init__.py
bernn/dl/models/pytorch/aecnndann.py
bernn/dl/models/pytorch/aedann.py
bernn/dl/models/pytorch/aeekandann.py
bernn/dl/models/pytorch/aekandann.py
bernn/dl/models/pytorch/ekan/__init__.py
bernn/dl/models/pytorch/ekan/src/__init__.py
bernn/dl/models/pytorch/ekan/src/efficient_kan/__init__.py
bernn/dl/models/pytorch/ekan/src/efficient_kan/kan.py
bernn/dl/models/pytorch/utils/__init__.py
bernn/dl/models/pytorch/utils/dataset.py
bernn/dl/models/pytorch/utils/distributions.py
bernn/dl/models/pytorch/utils/loggings.py
bernn/dl/models/pytorch/utils/losses.py
bernn/dl/models/pytorch/utils/metrics.py
bernn/dl/models/pytorch/utils/plotting.py
bernn/dl/models/pytorch/utils/stochastic.py
bernn/dl/models/pytorch/utils/utils.py
bernn/dl/train/__init__.py
bernn/dl/train/aecnndann.py
bernn/dl/train/aedacnn.py
bernn/dl/train/data_getters.py
bernn/dl/train/dataset.py
bernn/dl/train/train_ae.py
bernn/dl/train/train_ae_classifier.py
bernn/dl/train/train_ae_classifier2.py
bernn/dl/train/train_ae_classifier_holdout.py
bernn/dl/train/train_ae_then_classifier.py
bernn/dl/train/train_ae_then_classifier_holdout.py
bernn/dl/train/train_aecnn_classifier_holdout.py
bernn/dl/train/train_resnet_classifier.py
bernn/dl/train/utils.py
bernn/dl/train/pytorch/__init__.py
bernn/dl/train/pytorch_to_remove/__init__.py
bernn/dl/train/pytorch_to_remove/aecnndann.py
bernn/dl/train/pytorch_to_remove/aedann.py
bernn/dl/train/pytorch_to_remove/aeekandann.py
bernn/dl/train/pytorch_to_remove/aekandann.py
bernn/dl/train/pytorch_to_remove/avekandann.py
bernn/dl/train/pytorch_to_remove/ekan/__init__.py
bernn/dl/train/pytorch_to_remove/ekan/src/__init__.py
bernn/dl/train/pytorch_to_remove/ekan/src/efficient_kan/__init__.py
bernn/dl/train/pytorch_to_remove/ekan/src/efficient_kan/kan.py
bernn/dl/train/pytorch_to_remove/utils/__init__.py
bernn-0.2.18.dist-info/METADATA
bernn-0.2.18.dist-info/WHEEL
bernn-0.2.18.dist-info/entry_points.txt
bernn-0.2.18.dist-info/top_level.txt
bernn-0.2.18.dist-info/RECORD
